minipassword/__init__.py
minipassword/box.py
minipassword/commands.py
minipassword-1.0.1.dist-info/LICENSE
minipassword-1.0.1.dist-info/METADATA
minipassword-1.0.1.dist-info/WHEEL
minipassword-1.0.1.dist-info/top_level.txt
minipassword-1.0.1.dist-info/zip-safe
minipassword-1.0.1.dist-info/RECORD
