Metadata-Version: 2.1
Name: minipassword
Version: 1.0.1
Summary: Mini Password is a command-line password manager.
Home-page: https://github.com/laonan/minipassword
Author: Laonan
Author-email: hello@laonan.net
Project-URL: Bug Tracker, https://github.com/laonan/minipassword/issues
Classifier: Programming Language :: Python :: 3
Classifier: License :: OSI Approved :: MIT License
Classifier: Operating System :: OS Independent
Requires-Python: >=3.6
License-File: LICENSE
Requires-Dist: simple-term-menu >=1.6.4
Requires-Dist: cryptography >=42.0.7
Requires-Dist: requests >=2.31.0
